Workbook

Sheet Read_Me
A1: Portfolio Project – Sales Performance & MIS Dashboard
A3: Project objective: demonstrate Excel data cleaning, formula-driven transformation, KPI reporting, and dashboarding for an MIS/Data Analyst role.
A4: Workflow: Raw_Data -> Cleaned_Data (formula-based) -> Excel_Dashboard.
A5: Raw_Data intentionally contains inconsistent capitalization, spaces, alternate city names, missing values, invalid quantities/prices, mixed date formats, and duplicate order IDs.
A6: Cleaning is formula-driven. Key formulas use TRIM, PROPER, IFERROR, IF, MAX, VALUE, DATEVALUE, SUMIFS, COUNTIF, and EDATE.
A7: Calculated business metrics: Gross Sales, Discount Amount, Net Sales, Estimated Cost, Profit, Profit Margin, and Order Month.
A8: Quality checks updated: duplicate Order_ID values are flagged in Cleaned_Data; common city-name variants are standardized.
A9: Dashboard KPI formulas: Profit Margin = Total Profit / Net Sales; Average Order Value = Net Sales / Total Orders.
A10: Note: non-positive quantities are floored to zero in the cleaned calculation and flagged as CHECK. Estimated costs use illustrative category assumptions.

Sheet Raw_Data
A1: Order_ID | B1: Order_Date | C1: Salesperson | D1: City | E1: Sales_Channel | F1: Customer_Segment | G1: Category | H1: Product | I1: Quantity | J1: Unit_Price | K1: Discount | L1: Order_Status
A2: ORD-10001 | B2: 13/06/2026 | C2: Ravi | D2: Mumbai | E2: Online | F2: Consumer | G2: Laptop | H2: Laptop Pro 14 | I2: -1 | J2: 61049 | K2: 0.1 | L2: Pending
A3: ORD-10002 | B3: 2026-07-15 | C3: Ravi | D3: chennai | E3: Corporate | F3: Consumer | G3: Keyboard | H3: Keyboard Wireless | I3: 5 | J3: 4140 | K3: 0 | L3: Returned
A4: ORD-10003 | B4: 2026-01-26 | C4: Priya | D4: MYSURU | E4: Retail Store | F4: Consumer | G4: Mouse | H4: Mouse Ergonomic | I4: 5 | J4: 2155 | K4: 0.15 | L4: Returned
A5: ORD-10004 | B5: 24/02/2026 | C5: Bhoomika | D5: DELHI | E5: Corporate | F5: SMB | G5: Headset | H5: Headset Office | I5: 3 | J5: 5258 | K5: 0.05 | L5: Delivered
A6: ORD-10005 | B6: 2026-01-17 | C6: Arjun | D6: mysuru | E6: retail store | F6: Consumer | G6: Mouse | H6: Mouse Ergonomic | I6: 2 | J6: 3486 | K6: 0.15 | L6: Cancelled
A7: ORD-10006 | B7: 2026-02-20 | C7: Bhoomika | D7: Hyderabad | E7: Corporate | F7: SMB | G7: Monitor | H7: Monitor 27 | I7: 8 | J7: 26378 | K7: 0 | L7: Delivered
A8: ORD-10007 | B8: 05/06/2026 | C8: arjun | D8: Pune | E8: Corporate | F8: SMB | G8: Mouse | H8: Mouse Wireless | I8: 8 | J8: 2494 | K8: 0 | L8: Delivered
A9: ORD-10008 | B9: 2026-02-03 | C9: Kiran | D9: Mysore | E9: Corporate | F9: Consumer | G9: Headset | H9: Headset Office | I9: 2 | J9: 2272 | K9: 0.15 | L9: Pending
A10: ORD-10009 | B10: 2026-04-29 | C10: Neha | D10: mysuru | E10: Online | F10: SMB | G10: Monitor | H10: Monitor 24 | I10: 1 | J10: 12208 | K10: 0 | L10: Delivered
A11: ORD-10010 | B11: 05/05/2026 | C11: priya | D11: MUMBAI | E11: Online | F11: SMB | G11: Monitor | H11: Monitor 24 | I11: 1 | J11: 10916 | K11: 0.1 | L11: Pending
A12: ORD-10011 | B12: 25/05/2026 | C12: Arjun | D12: Mumbai | E12: Online | F12: Consumer | G12: Headset | H12: Headset Wireless | I12: 3 | J12: 4742 | K12: 0.15 | L12: Returned
A13: ORD-10012 | B13: 23/04/2026 | C13: Priya | D13: mumbai | E13: Corporate | F13: Consumer | G13: Headset | H13: Headset Office | I13: 3 | J13: 2348 | K13: 0.05 | L13: Delivered
... A24: ORD-10023 | B24: 2026-06-01 | C24: arjun | D24: Mumbai | E24: Retail Store | F24: Enterprise | G24: Monitor | H24: Monitor 24 | I24: 7 | J24: 12966 | K24: 0.15 | L24: Delivered
A25: ORD-10024 | B25: 04/05/2026 | C25: Kiran | D25: mumbai | E25: Retail Store | F25: SMB | G25: Mouse | H25: Mouse Ergonomic | I25: 4 | K25: 0.08 | L25: Cancelled
A26: ORD-10025 | B26: 04/07/2026 | C26: Bhoomika | D26: pune | E26: Corporate | F26: Enterprise | G26: Mouse | H26: Mouse Ergonomic | I26: 5 | J26: 770 | K26: 0.02 | L26: Pending
A27: ORD-10026 | B27: 2026-07-15 | C27: Priya | D27: PUNE | E27: Online | F27: SMB | G27: Monitor | H27: Monitor 24 | I27: -2 | J27: 18060 | K27: 0.02 | L27: Delivered
A28: ORD-10027 | B28: 2026-01-14 | C28: Bhoomika | D28: CHENNAI | E28: Corporate | F28: Consumer | G28: Keyboard | H28: Keyboard Mechanical | I28: 1 | J28: 5228 | K28: 0.02 | L28: Delivered
A29: ORD-10028 | B29: 2026-01-16 | C29: priya | D29: chennai | E29: Corporate | F29: SMB | G29: Headset | H29: Headset Office | I29: 3 | J29: 2165 | K29: 0.02 | L29: Delivered
A30: ORD-10029 | B30: 28/08/2026 | C30: Bhoomika | D30: Chennai | E30: Retail Store | F30: Enterprise | G30: Monitor | H30: Monitor 27 | I30: 2 | J30: 16366 | K30: 0 | L30: Delivered
A31: ORD-10030 | B31: 2026-06-22 | C31: Kiran | D31: Bengaluru | E31: Online | F31: Enterprise | G31: Headset | H31: Headset Office | I31: 8 | J31: 5354 | K31: 0.05 | L31: Delivered
A32: ORD-10031 | B32: 2026-04-27 | C32: Arjun | D32: MUMBAI | E32: Retail Store | F32: SMB | G32: Laptop | H32: Laptop Air 13 | I32: 8 | J32: 66186 | K32: 0.08 | L32: Delivered
A33: ORD-10032 | B33: 10/02/2026 | C33: Neha | D33: bengaluru | E33: Corporate | F33: Enterprise | G33: Keyboard | H33: Keyboard Office | I33: 8 | J33: 1963 | K33: 0 | L33: Returned
A34: ORD-10033 | B34: 2026-07-17 | C34: Arjun | D34: MUMBAI | E34: Retail Store | F34: Enterprise | G34: Mouse | H34: Mouse Ergonomic | I34: 8 | J34: 3104 | K34: 0.02 | L34: Pending
A35: ORD-10034 | B35: 2026-04-09 | C35: Priya | D35: Bangalore | E35: Online | F35: Enterprise | G35: Monitor | H35: Monitor 27 | I35: 2 | J35: 25459 | K35: 0.1 | L35: Pending
A36: ORD-10035 | B36: 14/07/2026 | C36: Ravi | D36: BENGALURU | E36: online | F36: SMB | G36: Mouse | H36: Mouse Basic | I36: 7 | J36: 1631 | K36: 0 | L36: Returned
A37: ORD-10036 | B37: 2026-04-08 | C37: Neha | D37: pune | E37: Online | F37: Enterprise | G37: Headset | H37: Headset Office | I37: 5 | J37: 6725 | K37: 0.08 | L37: Delivered
... A53: ORD-10052 | B53: 29/03/2026 | C53: Kiran | D53: Hyderabad | E53: corporate | F53: Consumer | G53: Laptop | H53: Business Laptop 15 | I53: 3 | J53: 47565 | K53: 0.05 | L53: Delivered
A54: ORD-10053 | C54: Arjun | D54: Hydrabad | E54: Corporate | F54: Consumer | G54: Keyboard | H54: Keyboard Wireless | I54: 2 | J54: 4410 | K54: 0.05 | L54: Cancelled
A55: ORD-10054 | B55: 2026-02-05 | C55: Priya | D55: MUMBAI | E55: Online | F55: SMB | G55: Monitor | H55: Monitor 24 | I55: 3 | J55: 25635 | K55: 0.1 | L55: Pending
A56: ORD-10055 | B56: 20/07/2026 | C56: Priya | D56: Delhi | E56: Retail Store | F56: Consumer | G56: Mouse | H56: Mouse Wireless | I56: 7 | J56: 1854 | K56: 0.02 | L56: Delivered
A57: ORD-10056 | B57: 2026-02-26 | C57: Asha | D57: BENGALURU | E57: Corporate | F57: SMB | G57: Mouse | H57: Mouse Ergonomic | I57: 4 | J57: 2756 | K57: 0.08 | L57: Delivered
A58: ORD-10057 | B58: 2026-01-05 | C58: Kiran | D58: Hyderabad | E58: Online | F58: Enterprise | G58: Keyboard | H58: Keyboard Wireless | I58: 4 | K58: 0.05 | L58: Delivered
A59: ORD-10058 | B59: 2026-02-17 | C59: Kiran | D59: Delhi | E59: Online | F59: SMB | G59: Laptop | H59: Business Laptop 15 | I59: 1 | J59: 49435 | K59: 0.08 | L59: Pending
A60: ORD-10059 | B60: 2026-07-19 | C60: Asha | D60: Mysuru | E60: Retail Store | F60: Consumer | G60: Mouse | H60: Mouse Basic | I60: 5 | J60: 2574 | K60: 0.02 | L60: Delivered
A61: ORD-10060 | B61: 05/04/2026 | C61: Ravi | D61: mysuru | E61: Corporate | F61: SMB | G61: Mouse | H61: Mouse Ergonomic | I61: 8 | J61: 2732 | K61: 0.05 | L61: Cancelled
A62: ORD-10061 | B62: 25/04/2026 | C62: Priya | D62: Delhi | E62: Corporate | F62: Enterprise | G62: Laptop | H62: Business Laptop 15 | I62: 7 | J62: 73504 | K62: 0.05 | L62: Cancelled
A63: ORD-10062 | B63: 2026-04-05 | C63: Priya | D63: CHENNAI | E63: Corporate | F63: Enterprise | G63: Keyboard | H63: Keyboard Mechanical | I63: 5 | J63: 4206 | K63: 0.02 | L63: Delivered
A64: ORD-10063 | B64: 2026-08-19 | C64: Meghana | D64: New Delhi | E64: retail store | F64: Consumer | G64: Mouse | H64: Mouse Wireless | I64: 3 | J64: 1928 | K64: 0.05 | L64: Cancelled
A65: ORD-10064 | B65: 15/05/2026 | C65: Priya | D65: CHENNAI | E65: Corporate | F65: SMB | G65: Mouse | H65: Mouse Ergonomic | I65: 6 | J65: 2543 | K65: 0.02 | L65: Cancelled
A66: ORD-10065 | B66: 2026-01-21 | C66: Arjun | D66: mumbai | E66: Online | F66: Consumer | G66: Keyboard | H66: Keyboard Wireless | I66: 3 | J66: 1965 | K66: 0.1 | L66: Cancelled
A67: ORD-10066 | B67: 2026-03-19 | C67: Arjun | D67: KOCHI | E67: Corporate | F67: Enterprise | G67: Mouse | H67: Mouse Wireless | I67: 8 | J67: 945 | K67: 0.08 | L67: Pending
A68: ORD-10067 | B68: 13/01/2026 | C68: Neha | D68: KOCHI | E68: Online | F68: Enterprise | G68: Keyboard | H68: Keyboard Mechanical | I68: 6 | J68: 3882 | K68: 0.02 | L68: Delivered
A69: ORD-10068 | B69: 18/05/2026 | C69: Meghana | D69: Kochi | E69: Retail Store | F69: Consumer | G69: Laptop | H69: Laptop Pro 14 | I69: 1 | J69: 53777 | K69: 0.08 | L69: Delivered
A70: ORD-10069 | B70: 2026-06-04 | C70: Priya | D70: BENGALURU | E70: Online | F70: Consumer | G70: Headset | H70: Headset Wireless | I70: 8 | J70: 5380 | L70: Cancelled
A71: ORD-10070 | B71: 26/03/2026 | C71: Priya | D71: Mumbai | E71: Retail Store | F71: Consumer | G71: Laptop | H71: Laptop Air 13 | I71: 4 | J71: 46746 | K71: 0.15 | L71: Delivered
A72: ORD-10071 | B72: 01/05/2026 | C72: Arjun | D72: Hydrabad | E72: Corporate | F72: Consumer | G72: Laptop | H72: Business Laptop 15 | I72: 7 | J72: 78992 | K72: 0.05 | L72: Delivered
A73: ORD-10072 | B73: 23/02/2026 | C73: Priya | D73: Mysore | E73: Corporate | F73: Enterprise | G73: Mouse | H73: Mouse Ergonomic | I73: 7 | J73: 1878 | K73: 0.08 | L73: Delivered
A74: ORD-10073 | B74: 2026-03-03 | C74: Asha | D74: PUNE | E74: Online | F74: Enterprise | G74: Monitor | H74: Monitor 24 | I74: 8 | J74: 10720 | K74: 0 | L74: Returned
A75: ORD-10074 | B75: 2026-07-09 | C75: Ravi | D75: KOCHI | E75: Retail Store | F75: Consumer | G75: Laptop | H75: Laptop Pro 14 | I75: 5 | J75: 56520 | K75: 0 | L75: Delivered
A76: ORD-10075 | B76: 17/02/2026 | C76: Kiran | D76: New Delhi | E76: Online | F76: SMB | G76: Laptop | H76: Business Laptop 15 | I76: 7 | J76: N/A | K76: 0.08 | L76: Cancelled
A77: ORD-10076 | B77: 27/06/2026 | C77: Bhoomika | D77: chennai | E77: Online | F77: Enterprise | G77: Monitor | H77: Monitor 24 | I77: 5 | J77: 19053 | K77: 0.15 | L77: Delivered
A78: ORD-10077 | B78: 13/07/2026 | C78: Priya | D78: Mysore | E78: Retail Store | F78: SMB | G78: Headset | H78: Headset Pro | I78: 1 | J78: 2419 | K78: 0.1 | L78: Cancelled
A79: ORD-10078 | B79: 29/04/2026 | C79: Ravi | D79: Bangalore | E79: Online | F79: Enterprise | G79: Keyboard | H79: Keyboard Office | I79: 2 | J79: 1224 | K79: 0 | L79: Pending
A80: ORD-10079 | B80: 2026-04-25 | C80: Meghana | D80: Chennai | E80: Retail Store | F80: Consumer | G80: Mouse | H80: Mouse Ergonomic | I80: 7 | J80: 1185 | K80: 0.1 | L80: Delivered
A81: ORD-10080 | B81: 27/07/2026 | C81: Asha | D81: Bengaluru | E81: Retail Store | F81: SMB | G81: Mouse | H81: Mouse Basic | I81: 1 | J81: 1113 | K81: 0.08 | L81: Cancelled
A82: ORD-10081 | B82: 2026-07-29 | C82: Priya | D82: Mumbai | E82: retail store | F82: Enterprise | G82: Keyboard | H82: Keyboard Wireless | I82: 5 | J82: 3010 | K82: 0 | L82: Cancelled
A83: ORD-10082 | B83: 06/08/2026 | C83: Arjun | D83: Hyderabad | E83: Retail Store | F83: Consumer | G83: Monitor | H83: Monitor 27 | I83: 3 | J83: 10888 | K83: 0.08 | L83: Delivered
A84: ORD-10083 | B84: 24/05/2026 | C84: Meghana | D84: pune | E84: Retail Store | F84: Enterprise | G84: Monitor | H84: Monitor 27 | I84: 2 | J84: 18934 | K84: 0.15 | L84: Pending
A85: ORD-10084 | B85: 23/03/2026 | C85: Kiran | D85: delhi | E85: Online | F85: SMB | G85: Monitor | H85: Monitor 27 | I85: 5 | J85: 10498 | K85: 0.1 | L85: Cancelled
A86: ORD-10085 | B86: 13/02/2026 | C86: Kiran | D86: Mysore | E86: Online | F86: SMB | G86: Monitor | H86: Monitor 32 | I86: 2 | J86: 26764 | L86: Delivered
A87: ORD-10086 | B87: 22/05/2026 | C87: Priya | D87: Bengaluru | E87: Retail Store | F87: Enterprise | G87: Mouse | H87: Mouse Wireless | I87: 7 | J87: 770 | K87: 0.02 | L87: Delivered
A88: ORD-10087 | B88: 17/06/2026 | C88: Kiran | D88: Cochin | E88: Online | F88: SMB | G88: Laptop | H88: Laptop Pro 14 | I88: 1 | J88: 69855 | K88: 0.15 | L88: Delivered
A89: ORD-10088 | B89: 06/08/2026 | C89: Kiran | D89: Pune | E89: Retail Store | F89: SMB | G89: Keyboard | H89: Keyboard Wireless | I89: 3 | J89: 4462 | K89: 0.1 | L89: Delivered
A90: ORD-10089 | B90: 2026-06-02 | C90: Kiran | D90: Bangalore | E90: Online | F90: SMB | G90: Mouse | H90: Mouse Ergonomic | I90: 7 | J90: N/A | K90: 0.08 | L90: Delivered
A91: ORD-10090 | B91: 2026-04-03 | C91: Ravi | D91: Hyderabad | E91: retail store | F91: Enterprise | G91: Keyboard | H91: Keyboard Wireless | I91: 7 | J91: 4730 | K91: 0 | L91: Delivered
A92: ORD-10091 | C92: Arjun | D92: Mysuru | E92: Corporate | F92: Consumer | G92: Keyboard | H92: Keyboard Mechanical | I92: 7 | J92: 2569 | K92: 0.05 | L92: Pending
A93: ORD-10092 | B93: 2026-04-21 | C93: Neha | D93: MUMBAI | E93: Retail Store | F93: Enterprise | G93: Headset | H93: Headset Pro | I93: 7 | J93: 2955 | K93: 0.05 | L93: Delivered
A94: ORD-10093 | B94: 23/04/2026 | C94: Kiran | D94: Chennai | E94: Corporate | F94: Enterprise | G94: Keyboard | H94: Keyboard Office | I94: 4 | J94: 2340 | K94: 0.05 | L94: Returned
A95: ORD-10094 | B95: 16/07/2026 | C95: Meghana | D95: Delhi | E95: Corporate | F95: Consumer | G95: Monitor | H95: Monitor 32 | I95: 2 | J95: 10451 | K95: 0 | L95: Delivered
A96: ORD-10095 | B96: 29/03/2026 | C96: ravi | D96: MYSURU | E96: Online | F96: SMB | G96: Mouse | H96: Mouse Wireless | I96: 8 | J96: 2494 | K96: 0.05 | L96: Delivered
A97: ORD-10096 | B97: 17/02/2026 | C97: Ravi | D97: Bengaluru | E97: Corporate | F97: Enterprise | G97: Mouse | H97: Mouse Ergonomic | I97: 4 | J97: 2292 | K97: 0.02 | L97: Delivered
A98: ORD-10097 | B98: 2026-03-31 | C98: Priya | D98: HYDERABAD | E98: Online | F98: Enterprise | G98: Keyboard | H98: Keyboard Mechanical | I98: 4 | J98: 2297 | K98: 0.05 | L98: Delivered
A99: ORD-10098 | B99: 03/01/2026 | C99: Neha | D99: pune | E99: Online | F99: SMB | G99: Mouse | H99: Mouse Wireless | I99: 7 | J99: 3374 | K99: 0.15 | L99: Pending
A100: ORD-10099 | B100: 2026-05-27 | C100: Meghana | D100: Delhi | E100: Retail Store | F100: SMB | G100: Laptop | H100: Laptop Air 13 | I100: 7 | J100: 80523 | K100: 0 | L100: Returned
A101: ORD-10100 | B101: 2026-02-12 | C101: Bhoomika | D101: Pune | E101: Corporate | F101: SMB | G101: Headset | H101: Headset Pro | I101: 3 | J101: 3802 | K101: 0.05 | L101: Returned
A102: ORD-10101 | C102: Ravi | D102: Cochin | E102: Corporate | F102: Enterprise | G102: Monitor | H102: Monitor 32 | I102: 7 | J102: 13658 | K102: 0.08 | L102: Delivered
A103: ORD-10102 | B103: 02/04/2026 | C103: Priya | D103: Cochin | E103: Retail Store | F103: SMB | G103: Laptop | H103: Business Laptop 15 | I103: 6 | J103: 59275 | K103: 0.05 | L103: Delivered
A104: ORD-10103 | C104: priya | D104: Mumbai | E104: Corporate | F104: SMB | G104: Monitor | H104: Monitor 32 | I104: 5 | J104: 17979 | L104: Delivered
A105: ORD-10104 | B105: 2026-06-28 | C105: Arjun | D105: Kochi | E105: Online | F105: Consumer | G105: Keyboard | H105: Keyboard Wireless | I105: 2 | J105: 1780 | K105: 0.15 | L105: Delivered
A106: ORD-10105 | B106: 24/04/2026 | C106: Ravi | D106: chennai | E106: Corporate | F106: Consumer | G106: Monitor | H106: Monitor 24 | I106: 6 | J106: 13035 | K106: 0.02 | L106: Delivered
A107: ORD-10106 | B107: 03/03/2026 | C107: Kiran | D107: Chennai | E107: Retail Store | F107: SMB | G107: Mouse | H107: Mouse Ergonomic | I107: 6 | J107: 2863 | K107: 0.05 | L107: Delivered
A108: ORD-10107 | B108: 16/07/2026 | C108: Priya | D108: Kochi | E108: Corporate | F108: Consumer | G108: Mouse | H108: Mouse Ergonomic | I108: 5 | J108: 1836 | K108: 0 | L108: Cancelled
A109: ORD-10108 | B109: 06/06/2026 | C109: Bhoomika | D109: Mumbai | E109: Retail Store | F109: SMB | G109: Headset | H109: Headset Pro | I109: 1 | J109: 7246 | K109: 0.02 | L109: Pending
A110: ORD-10109 | B110: 11/05/2026 | C110: Meghana | D110: MYSURU | E110: Online | F110: Enterprise | G110: Keyboard | H110: Keyboard Wireless | I110: 2 | J110: 4212 | K110: 0.1 | L110: Returned
A111: ORD-10110 | B111: 05/03/2026 | C111: Asha | D111: New Delhi | E111: Retail Store | F111: Enterprise | G111: Mouse | H111: Mouse Basic | I111: 1 | J111: 1189 | K111: 0.02 | L111: Delivered
A112: ORD-10111 | B112: 07/05/2026 | C112: arjun | D112: PUNE | E112: Corporate | F112: SMB | G112: Monitor | H112: Monitor 32 | I112: 6 | J112: 9208 | K112: 0.15 | L112: Returned
A113: ORD-10112 | B113: 2026-08-05 | C113: Kiran | D113: New Delhi | E113: Retail Store | F113: Enterprise | G113: Headset | H113: Headset Wireless | I113: 7 | J113: 2593 | K113: 0 | L113: Cancelled
A114: ORD-10113 | B114: 30/05/2026 | C114: Meghana | D114: Chennai | E114: Online | F114: Consumer | G114: Laptop | H114: Laptop Pro 14 | I114: 2 | J114: 55772 | K114: 0.1 | L114: Delivered
A115: ORD-10114 | B115: 18/03/2026 | C115: Meghana | D115: Bangalore | E115: Retail Store | F115: Consumer | G115: Keyboard | H115: Keyboard Wireless | I115: 2 | J115: 3246 | K115: 0.02 | L115: Delivered
A116: ORD-10115 | B116: 2026-08-20 | C116: Kiran | D116: Bengaluru | E116: Online | F116: Enterprise | G116: Keyboard | H116: Keyboard Wireless | I116: 7 | J116: 2576 | K116: 0.08 | L116: Delivered
... A135: ORD-10134 | B135: 21/07/2026 | C135: Arjun | D135: KOCHI | E135: Corporate | F135: Consumer | G135: Laptop | H135: Laptop Pro 14 | I135: 1 | J135: 73141 | K135: 0 | L135: Cancelled
A136: ORD-10135 | C136: Meghana | D136: MYSURU | E136: retail store | F136: SMB | G136: Keyboard | H136: Keyboard Mechanical | I136: 3 | J136: 3967 | K136: 0.05 | L136: Pending
A137: ORD-10136 | B137: 13/06/2026 | C137: Kiran | D137: Bengaluru | E137: Corporate | F137: Consumer | G137: Keyboard | H137: Keyboard Office | I137: 1 | J137: 2085 | K137: 0.15 | L137: Delivered
A138: ORD-10137 | C138: Arjun | D138: Chennai | E138: Online | F138: SMB | G138: Headset | H138: Headset Office | I138: 4 | J138: 3127 | K138: 0.05 | L138: Cancelled
A139: ORD-10138 | B139: 24/01/2026 | C139: Asha | D139: Chennai | E139: Corporate | F139: Consumer | G139: Headset | H139: Headset Pro | I139: 8 | J139: 3663 | K139: 0 | L139: Delivered
A140: ORD-10139 | B140: 07/07/2026 | C140: Kiran | D140: DELHI | E140: Online | F140: Consumer | G140: Laptop | H140: Laptop Air 13 | I140: 5 | J140: 56984 | K140: 0.08 | L140: Returned
A141: ORD-10140 | B141: 06/06/2026 | C141: Asha | D141: hyderabad | E141: Corporate | F141: Consumer | G141: Laptop | H141: Business Laptop 15 | I141: 1 | J141: 76659 | K141: 0 | L141: Delivered
A142: ORD-10141 | B142: 14/06/2026 | C142: Arjun | D142: bengaluru | E142: Online | F142: Enterprise | G142: Mouse | H142: Mouse Wireless | I142: 3 | J142: 2622 | K142: 0 | L142: Pending
A143: ORD-10142 | B143: 2026-07-10 | C143: Neha | D143: Cochin | E143: Online | F143: Enterprise | G143: Laptop | H143: Laptop Pro 14 | I143: 5 | J143: N/A | K143: 0.1 | L143: Cancelled
...

Sheet Cleaned_Data
A1: Order_ID | B1: Order_Date | C1: Salesperson | D1: City | E1: Sales_Channel | F1: Customer_Segment | G1: Category | H1: Product | I1: Quantity | J1: Unit_Price | K1: Discount | L1: Order_Status | M1: Gross_Sales | N1: Discount_Amount | O1: Net_Sales | P1: Estimated_Cost | Q1: Profit | R1: Profit_Margin | S1: Order_Month | T1: Data_Quality_Flag
A2: =TRIM(Raw_Data!A2) -> ORD-10001 | B2: =IFERROR(IF(ISNUMBER(Raw_Data!B2),Raw_Data!B2,DATEVALUE(Raw_Data!B2)),"") -> 46186 | C2: =PROPER(TRIM(Raw_Data!C2)) -> Ravi | D2: =IF(TRIM(Raw_Data!D2)="Bangalore","Bengaluru",IF(TRIM(Raw_Data!D2)="Mysore","Mysuru",IF(TRIM(Raw_Data!D2)="Cochin","Kochi",PROPER(TRIM(Raw_Data!D2))))) -> Mumbai | E2: =PROPER(TRIM(Raw_Data!E2)) -> Online | F2: =PROPER(TRIM(Raw_Data!F2)) -> Consumer | G2: =PROPER(TRIM(Raw_Data!G2)) -> Laptop | H2: =PROPER(TRIM(Raw_Data!H2)) -> Laptop Pro 14 | I2: =IFERROR(MAX(0,VALUE(Raw_Data!I2)),0) -> 0 | J2: =IFERROR(VALUE(Raw_Data!J2),0) -> 61049 | K2: =IFERROR(VALUE(Raw_Data!K2),0) -> 0.1 | L2: =PROPER(TRIM(Raw_Data!L2)) -> Pending | M2: =I2*J2 -> 0 | N2: =M2*K2 -> 0 | O2: =M2-N2 -> 0 | P2: =M2*IF(G2="Laptop",0.78,IF(G2="Monitor",0.7,IF(G2="Keyboard",0.58,IF(G2="Mouse",0.55,0.6)))) -> 0 | Q2: =O2-P2 -> 0 | R2: =IFERROR(Q2/O2,0) -> 0 | S2: =IF(B2="","",TEXT(B2,"mmm-yyyy")) -> Jun-2026 | T2: =IF(OR(A2="",B2="",I2<=0,J2<=0,L2=""),"CHECK","OK") -> CHECK
A3: =TRIM(Raw_Data!A3) -> ORD-10002 | B3: =IFERROR(IF(ISNUMBER(Raw_Data!B3),Raw_Data!B3,DATEVALUE(Raw_Data!B3)),"") -> 46218 | C3: =PROPER(TRIM(Raw_Data!C3)) -> Ravi | D3: =IF(TRIM(Raw_Data!D3)="Bangalore","Bengaluru",IF(TRIM(Raw_Data!D3)="Mysore","Mysuru",IF(TRIM(Raw_Data!D3)="Cochin","Kochi",PROPER(TRIM(Raw_Data!D3))))) -> Chennai | E3: =PROPER(TRIM(Raw_Data!E3)) -> Corporate | F3: =PROPER(TRIM(Raw_Data!F3)) -> Consumer | G3: =PROPER(TRIM(Raw_Data!G3)) -> Keyboard | H3: =PROPER(TRIM(Raw_Data!H3)) -> Keyboard Wireless | I3: =IFERROR(MAX(0,VALUE(Raw_Data!I3)),0) -> 5 | J3: =IFERROR(VALUE(Raw_Data!J3),0) -> 4140 | K3: =IFERROR(VALUE(Raw_Data!K3),0) -> 0 | L3: =PROPER(TRIM(Raw_Data!L3)) -> Returned | M3: =I3*J3 -> 20700 | N3: =M3*K3 -> 0 | O3: =M3-N3 -> 20700 | P3: =M3*IF(G3="Laptop",0.78,IF(G3="Monitor",0.7,IF(G3="Keyboard",0.58,IF(G3="Mouse",0.55,0.6)))) -> 12006 | Q3: =O3-P3 -> 8694 | R3: =IFERROR(Q3/O3,0) -> 0.42 | S3: =IF(B3="","",TEXT(B3,"mmm-yyyy")) -> Jul-2026 | T3: =IF(OR(A3="",B3="",I3<=0,J3<=0,L3=""),"CHECK","OK") -> OK
A4: =TRIM(Raw_Data!A4) -> ORD-10003 | B4: =IFERROR(IF(ISNUMBER(Raw_Data!B4),Raw_Data!B4,DATEVALUE(Raw_Data!B4)),"") -> 46048 | C4: =PROPER(TRIM(Raw_Data!C4)) -> Priya | D4: =IF(TRIM(Raw_Data!D4)="Bangalore","Bengaluru",IF(TRIM(Raw_Data!D4)="Mysore","Mysuru",IF(TRIM(Raw_Data!D4)="Cochin","Kochi",PROPER(TRIM(Raw_Data!D4))))) -> Mysuru | E4: =PROPER(TRIM(Raw_Data!E4)) -> Retail Store | F4: =PROPER(TRIM(Raw_Data!F4)) -> Consumer | G4: =PROPER(TRIM(Raw_Data!G4)) -> Mouse | H4: =PROPER(TRIM(Raw_Data!H4)) -> Mouse Ergonomic | I4: =IFERROR(MAX(0,VALUE(Raw_Data!I4)),0) -> 5 | J4: =IFERROR(VALUE(Raw_Data!J4),0) -> 2155 | K4: =IFERROR(VALUE(Raw_Data!K4),0) -> 0.15 | L4: =PROPER(TRIM(Raw_Data!L4)) -> Returned | M4: =I4*J4 -> 10775 | N4: =M4*K4 -> 1616.25 | O4: =M4-N4 -> 9158.75 | P4: =M4*IF(G4="Laptop",0.78,IF(G4="Monitor",0.7,IF(G4="Keyboard",0.58,IF(G4="Mouse",0.55,0.6)))) -> 5926.25 | Q4: =O4-P4 -> 3232.5 | R4: =IFERROR(Q4/O4,0) -> 0.35294118 | S4: =IF(B4="","",TEXT(B4,"mmm-yyyy")) -> Jan-2026 | T4: =IF(OR(A4="",B4="",I4<=0,J4<=0,L4=""),"CHECK","OK") -> OK
A5: =TRIM(Raw_Data!A5) -> ORD-10004 | B5: =IFERROR(IF(ISNUMBER(Raw_Data!B5),Raw_Data!B5,DATEVALUE(Raw_Data!B5)),"") -> 46077 | C5: =PROPER(TRIM(Raw_Data!C5)) -> Bhoomika | D5: =IF(TRIM(Raw_Data!D5)="Bangalore","Bengaluru",IF(TRIM(Raw_Data!D5)="Mysore","Mysuru",IF(TRIM(Raw_Data!D5)="Cochin","Kochi",PROPER(TRIM(Raw_Data!D5))))) -> Delhi | E5: =PROPER(TRIM(Raw_Data!E5)) -> Corporate | F5: =PROPER(TRIM(Raw_Data!F5)) -> Smb | G5: =PROPER(TRIM(Raw_Data!G5)) -> Headset | H5: =PROPER(TRIM(Raw_Data!H5)) -> Headset Office | I5: =IFERROR(MAX(0,VALUE(Raw_Data!I5)),0) -> 3 | J5: =IFERROR(VALUE(Raw_Data!J5),0) -> 5258 | K5: =IFERROR(VALUE(Raw_Data!K5),0) -> 0.05 | L5: =PROPER(TRIM(Raw_Data!L5)) -> Delivered | M5: =I5*J5 -> 15774 | N5: =M5*K5 -> 788.7 | O5: =M5-N5 -> 14985.3 | P5: =M5*IF(G5="Laptop",0.78,IF(G5="Monitor",0.7,IF(G5="Keyboard",0.58,IF(G5="Mouse",0.55,0.6)))) -> 9464.4 | Q5: =O5-P5 -> 5520.9 | R5: =IFERROR(Q5/O5,0) -> 0.36842105 | S5: =IF(B5="","",TEXT(B5,"mmm-yyyy")) -> Feb-2026 | T5: =IF(OR(A5="",B5="",I5<=0,J5<=0,L5=""),"CHECK","OK") -> OK
A6: =TRIM(Raw_Data!A6) -> ORD-10005 | B6: =IFERROR(IF(ISNUMBER(Raw_Data!B6),Raw_Data!B6,DATEVALUE(Raw_Data!B6)),"") -> 46039 | C6: =PROPER(TRIM(Raw_Data!C6)) -> Arjun | D6: =IF(TRIM(Raw_Data!D6)="Bangalore","Bengaluru",IF(TRIM(Raw_Data!D6)="Mysore","Mysuru",IF(TRIM(Raw_Data!D6)="Cochin","Kochi",PROPER(TRIM(Raw_Data!D6))))) -> Mysuru | E6: =PROPER(TRIM(Raw_Data!E6)) -> Retail Store | F6: =PROPER(TRIM(Raw_Data!F6)) -> Consumer | G6: =PROPER(TRIM(Raw_Data!G6)) -> Mouse | H6: =PROPER(TRIM(Raw_Data!H6)) -> Mouse Ergonomic | I6: =IFERROR(MAX(0,VALUE(Raw_Data!I6)),0) -> 2 | J6: =IFERROR(VALUE(Raw_Data!J6),0) -> 3486 | K6: =IFERROR(VALUE(Raw_Data!K6),0) -> 0.15 | L6: =PROPER(TRIM(Raw_Data!L6)) -> Cancelled | M6: =I6*J6 -> 6972 | N6: =M6*K6 -> 1045.8 | O6: =M6-N6 -> 5926.2 | P6: =M6*IF(G6="Laptop",0.78,IF(G6="Monitor",0.7,IF(G6="Keyboard",0.58,IF(G6="Mouse",0.55,0.6)))) -> 3834.6 | Q6: =O6-P6 -> 2091.6 | R6: =IFERROR(Q6/O6,0) -> 0.35294118 | S6: =IF(B6="","",TEXT(B6,"mmm-yyyy")) -> Jan-2026 | T6: =IF(OR(A6="",B6="",I6<=0,J6<=0,L6=""),"CHECK","OK") -> OK
A7: =TRIM(Raw_Data!A7) -> ORD-10006 | B7: =IFERROR(IF(ISNUMBER(Raw_Data!B7),Raw_Data!B7,DATEVALUE(Raw_Data!B7)),"") -> 46073 | C7: =PROPER(TRIM(Raw_Data!C7)) -> Bhoomika | D7: =IF(TRIM(Raw_Data!D7)="Bangalore","Bengaluru",IF(TRIM(Raw_Data!D7)="Mysore","Mysuru",IF(TRIM(Raw_Data!D7)="Cochin","Kochi",PROPER(TRIM(Raw_Data!D7))))) -> Hyderabad | E7: =PROPER(TRIM(Raw_Data!E7)) -> Corporate | F7: =PROPER(TRIM(Raw_Data!F7)) -> Smb | G7: =PROPER(TRIM(Raw_Data!G7)) -> Monitor | H7: =PROPER(TRIM(Raw_Data!H7)) -> Monitor 27 | I7: =IFERROR(MAX(0,VALUE(Raw_Data!I7)),0) -> 8 | J7: =IFERROR(VALUE(Raw_Data!J7),0) -> 26378 | K7: =IFERROR(VALUE(Raw_Data!K7),0) -> 0 | L7: =PROPER(TRIM(Raw_Data!L7)) -> Delivered | M7: =I7*J7 -> 211024 | N7: =M7*K7 -> 0 | O7: =M7-N7 -> 211024 | P7: =M7*IF(G7="Laptop",0.78,IF(G7="Monitor",0.7,IF(G7="Keyboard",0.58,IF(G7="Mouse",0.55,0.6)))) -> 147716.8 | Q7: =O7-P7 -> 63307.2 | R7: =IFERROR(Q7/O7,0) -> 0.3 | S7: =IF(B7="","",TEXT(B7,"mmm-yyyy")) -> Feb-2026 | T7: =IF(OR(A7="",B7="",I7<=0,J7<=0,L7=""),"CHECK","OK") -> OK
A8: =TRIM(Raw_Data!A8) -> ORD-10007 | B8: =IFERROR(IF(ISNUMBER(Raw_Data!B8),Raw_Data!B8,DATEVALUE(Raw_Data!B8)),"") -> 46178 | C8: =PROPER(TRIM(Raw_Data!C8)) -> Arjun | D8: =IF(TRIM(Raw_Data!D8)="Bangalore","Bengaluru",IF(TRIM(Raw_Data!D8)="Mysore","Mysuru",IF(TRIM(Raw_Data!D8)="Cochin","Kochi",PROPER(TRIM(Raw_Data!D8))))) -> Pune | E8: =PROPER(TRIM(Raw_Data!E8)) -> Corporate | F8: =PROPER(TRIM(Raw_Data!F8)) -> Smb | G8: =PROPER(TRIM(Raw_Data!G8)) -> Mouse | H8: =PROPER(TRIM(Raw_Data!H8)) -> Mouse Wireless | I8: =IFERROR(MAX(0,VALUE(Raw_Data!I8)),0) -> 8 | J8: =IFERROR(VALUE(Raw_Data!J8),0) -> 2494 | K8: =IFERROR(VALUE(Raw_Data!K8),0) -> 0 | L8: =PROPER(TRIM(Raw_Data!L8)) -> Delivered | M8: =I8*J8 -> 19952 | N8: =M8*K8 -> 0 | O8: =M8-N8 -> 19952 | P8: =M8*IF(G8="Laptop",0.78,IF(G8="Monitor",0.7,IF(G8="Keyboard",0.58,IF(G8="Mouse",0.55,0.6)))) -> 10973.6 | Q8: =O8-P8 -> 8978.4 | R8: =IFERROR(Q8/O8,0) -> 0.45 | S8: =IF(B8="","",TEXT(B8,"mmm-yyyy")) -> Jun-2026 | T8: =IF(OR(A8="",B8="",I8<=0,J8<=0,L8=""),"CHECK","OK") -> OK
A9: =TRIM(Raw_Data!A9) -> ORD-10008 | B9: =IFERROR(IF(ISNUMBER(Raw_Data!B9),Raw_Data!B9,DATEVALUE(Raw_Data!B9)),"") -> 46056 | C9: =PROPER(TRIM(Raw_Data!C9)) -> Kiran | D9: =IF(TRIM(Raw_Data!D9)="Bangalore","Bengaluru",IF(TRIM(Raw_Data!D9)="Mysore","Mysuru",IF(TRIM(Raw_Data!D9)="Cochin","Kochi",PROPER(TRIM(Raw_Data!D9))))) -> Mysuru | E9: =PROPER(TRIM(Raw_Data!E9)) -> Corporate | F9: =PROPER(TRIM(Raw_Data!F9)) -> Consumer | G9: =PROPER(TRIM(Raw_Data!G9)) -> Headset | H9: =PROPER(TRIM(Raw_Data!H9)) -> Headset Office | I9: =IFERROR(MAX(0,VALUE(Raw_Data!I9)),0) -> 2 | J9: =IFERROR(VALUE(Raw_Data!J9),0) -> 2272 | K9: =IFERROR(VALUE(Raw_Data!K9),0) -> 0.15 | L9: =PROPER(TRIM(Raw_Data!L9)) -> Pending | M9: =I9*J9 -> 4544 | N9: =M9*K9 -> 681.6 | O9: =M9-N9 -> 3862.4 | P9: =M9*IF(G9="Laptop",0.78,IF(G9="Monitor",0.7,IF(G9="Keyboard",0.58,IF(G9="Mouse",0.55,0.6)))) -> 2726.4 | Q9: =O9-P9 -> 1136 | R9: =IFERROR(Q9/O9,0) -> 0.29411765 | S9: =IF(B9="","",TEXT(B9,"mmm-yyyy")) -> Feb-2026 | T9: =IF(OR(A9="",B9="",I9<=0,J9<=0,L9=""),"CHECK","OK") -> OK
A10: =TRIM(Raw_Data!A10) -> ORD-10009 | B10: =IFERROR(IF(ISNUMBER(Raw_Data!B10),Raw_Data!B10,DATEVALUE(Raw_Data!B10)),"") -> 46141 | C10: =PROPER(TRIM(Raw_Data!C10)) -> Neha | D10: =IF(TRIM(Raw_Data!D10)="Bangalore","Bengaluru",IF(TRIM(Raw_Data!D10)="Mysore","Mysuru",IF(TRIM(Raw_Data!D10)="Cochin","Kochi",PROPER(TRIM(Raw_Data!D10))))) -> Mysuru | E10: =PROPER(TRIM(Raw_Data!E10)) -> Online | F10: =PROPER(TRIM(Raw_Data!F10)) -> Smb | G10: =PROPER(TRIM(Raw_Data!G10)) -> Monitor | H10: =PROPER(TRIM(Raw_Data!H10)) -> Monitor 24 | I10: =IFERROR(MAX(0,VALUE(Raw_Data!I10)),0) -> 1 | J10: =IFERROR(VALUE(Raw_Data!J10),0) -> 12208 | K10: =IFERROR(VALUE(Raw_Data!K10),0) -> 0 | L10: =PROPER(TRIM(Raw_Data!L10)) -> Delivered | M10: =I10*J10 -> 12208 | N10: =M10*K10 -> 0 | O10: =M10-N10 -> 12208 | P10: =M10*IF(G10="Laptop",0.78,IF(G10="Monitor",0.7,IF(G10="Keyboard",0.58,IF(G10="Mouse",0.55,0.6)))) -> 8545.6 | Q10: =O10-P10 -> 3662.4 | R10: =IFERROR(Q10/O10,0) -> 0.3 | S10: =IF(B10="","",TEXT(B10,"mmm-yyyy")) -> Apr-2026 | T10: =IF(OR(A10="",B10="",I10<=0,J10<=0,L10=""),"CHECK","OK") -> OK
A11: =TRIM(Raw_Data!A11) -> ORD-10010 | B11: =IFERROR(IF(ISNUMBER(Raw_Data!B11),Raw_Data!B11,DATEVALUE(Raw_Data!B11)),"") -> 46147 | C11: =PROPER(TRIM(Raw_Data!C11)) -> Priya | D11: =IF(TRIM(Raw_Data!D11)="Bangalore","Bengaluru",IF(TRIM(Raw_Data!D11)="Mysore","Mysuru",IF(TRIM(Raw_Data!D11)="Cochin","Kochi",PROPER(TRIM(Raw_Data!D11))))) -> Mumbai | E11: =PROPER(TRIM(Raw_Data!E11)) -> Online | F11: =PROPER(TRIM(Raw_Data!F11)) -> Smb | G11: =PROPER(TRIM(Raw_Data!G11)) -> Monitor | H11: =PROPER(TRIM(Raw_Data!H11)) -> Monitor 24 | I11: =IFERROR(MAX(0,VALUE(Raw_Data!I11)),0) -> 1 | J11: =IFERROR(VALUE(Raw_Data!J11),0) -> 10916 | K11: =IFERROR(VALUE(Raw_Data!K11),0) -> 0.1 | L11: =PROPER(TRIM(Raw_Data!L11)) -> Pending | M11: =I11*J11 -> 10916 | N11: =M11*K11 -> 1091.6 | O11: =M11-N11 -> 9824.4 | P11: =M11*IF(G11="Laptop",0.78,IF(G11="Monitor",0.7,IF(G11="Keyboard",0.58,IF(G11="Mouse",0.55,0.6)))) -> 7641.2 | Q11: =O11-P11 -> 2183.2 | R11: =IFERROR(Q11/O11,0) -> 0.22222222 | S11: =IF(B11="","",TEXT(B11,"mmm-yyyy")) -> May-2026 | T11: =IF(OR(A11="",B11="",I11<=0,J11<=0,L11=""),"CHECK","OK") -> OK
A12: =TRIM(Raw_Data!A12) -> ORD-10011 | B12: =IFERROR(IF(ISNUMBER(Raw_Data!B12),Raw_Data!B12,DATEVALUE(Raw_Data!B12)),"") -> 46167 | C12: =PROPER(TRIM(Raw_Data!C12)) -> Arjun | D12: =IF(TRIM(Raw_Data!D12)="Bangalore","Bengaluru",IF(TRIM(Raw_Data!D12)="Mysore","Mysuru",IF(TRIM(Raw_Data!D12)="Cochin","Kochi",PROPER(TRIM(Raw_Data!D12))))) -> Mumbai | E12: =PROPER(TRIM(Raw_Data!E12)) -> Online | F12: =PROPER(TRIM(Raw_Data!F12)) -> Consumer | G12: =PROPER(TRIM(Raw_Data!G12)) -> Headset | H12: =PROPER(TRIM(Raw_Data!H12)) -> Headset Wireless | I12: =IFERROR(MAX(0,VALUE(Raw_Data!I12)),0) -> 3 | J12: =IFERROR(VALUE(Raw_Data!J12),0) -> 4742 | K12: =IFERROR(VALUE(Raw_Data!K12),0) -> 0.15 | L12: =PROPER(TRIM(Raw_Data!L12)) -> Returned | M12: =I12*J12 -> 14226 | N12: =M12*K12 -> 2133.9 | O12: =M12-N12 -> 12092.1 | P12: =M12*IF(G12="Laptop",0.78,IF(G12="Monitor",0.7,IF(G12="Keyboard",0.58,IF(G12="Mouse",0.55,0.6)))) -> 8535.6 | Q12: =O12-P12 -> 3556.5 | R12: =IFERROR(Q12/O12,0) -> 0.29411765 | S12: =IF(B12="","",TEXT(B12,"mmm-yyyy")) -> May-2026 | T12: =IF(OR(A12="",B12="",I12<=0,J12<=0,L12=""),"CHECK","OK") -> OK
A13: =TRIM(Raw_Data!A13) -> ORD-10012 | B13: =IFERROR(IF(ISNUMBER(Raw_Data!B13),Raw_Data!B13,DATEVALUE(Raw_Data!B13)),"") -> 46135 | C13: =PROPER(TRIM(Raw_Data!C13)) -> Priya | D13: =IF(TRIM(Raw_Data!D13)="Bangalore","Bengaluru",IF(TRIM(Raw_Data!D13)="Mysore","Mysuru",IF(TRIM(Raw_Data!D13)="Cochin","Kochi",PROPER(TRIM(Raw_Data!D13))))) -> Mumbai | E13: =PROPER(TRIM(Raw_Data!E13)) -> Corporate | F13: =PROPER(TRIM(Raw_Data!F13)) -> Consumer | G13: =PROPER(TRIM(Raw_Data!G13)) -> Headset | H13: =PROPER(TRIM(Raw_Data!H13)) -> Headset Office | I13: =IFERROR(MAX(0,VALUE(Raw_Data!I13)),0) -> 3 | J13: =IFERROR(VALUE(Raw_Data!J13),0) -> 2348 | K13: =IFERROR(VALUE(Raw_Data!K13),0) -> 0.05 | L13: =PROPER(TRIM(Raw_Data!L13)) -> Delivered | M13: =I13*J13 -> 7044 | N13: =M13*K13 -> 352.2 | O13: =M13-N13 -> 6691.8 | P13: =M13*IF(G13="Laptop",0.78,IF(G13="Monitor",0.7,IF(G13="Keyboard",0.58,IF(G13="Mouse",0.55,0.6)))) -> 4226.4 | Q13: =O13-P13 -> 2465.4 | R13: =IFERROR(Q13/O13,0) -> 0.36842105 | S13: =IF(B13="","",TEXT(B13,"mmm-yyyy")) -> Apr-2026 | T13: =IF(OR(A13="",B13="",I13<=0,J13<=0,L13=""),"CHECK","OK") -> OK
... A651: =TRIM(Raw_Data!A651) -> ORD-10650 | B651: =IFERROR(IF(ISNUMBER(Raw_Data!B651),Raw_Data!B651,DATEVALUE(Raw_Data!B651)),"") -> 46199 | C651: =PROPER(TRIM(Raw_Data!C651)) -> Bhoomika | D651: =IF(TRIM(Raw_Data!D651)="Bangalore","Bengaluru",IF(TRIM(Raw_Data!D651)="Mysore","Mysuru",IF(TRIM(Raw_Data!D651)="Cochin","Kochi",PROPER(TRIM(Raw_Data!D651))))) -> Mumbai | E651: =PROPER(TRIM(Raw_Data!E651)) -> Corporate | F651: =PROPER(TRIM(Raw_Data!F651)) -> Smb | G651: =PROPER(TRIM(Raw_Data!G651)) -> Headset | H651: =PROPER(TRIM(Raw_Data!H651)) -> Headset Office | I651: =IFERROR(MAX(0,VALUE(Raw_Data!I651)),0) -> 1 | J651: =IFERROR(VALUE(Raw_Data!J651),0) -> 5154 | K651: =IFERROR(VALUE(Raw_Data!K651),0) -> 0 | L651: =PROPER(TRIM(Raw_Data!L651)) -> Returned | M651: =I651*J651 -> 5154 | N651: =M651*K651 -> 0 | O651: =M651-N651 -> 5154 | P651: =M651*IF(G651="Laptop",0.78,IF(G651="Monitor",0.7,IF(G651="Keyboard",0.58,IF(G651="Mouse",0.55,0.6)))) -> 3092.4 | Q651: =O651-P651 -> 2061.6 | R651: =IFERROR(Q651/O651,0) -> 0.4 | S651: =IF(B651="","",TEXT(B651,"mmm-yyyy")) -> Jun-2026 | T651: =IF(OR(A651="",B651="",I651<=0,J651<=0,L651=""),"CHECK","OK") -> OK

Sheet Excel_Dashboard
A1: SALES PERFORMANCE DASHBOARD
A4: Total Orders | C4: Net Sales | E4: Profit | G4: Profit Margin | I4: Avg Order Value
A5: =COUNTA(Cleaned_Data!A2:A651) -> 650 | C5: =SUM(Cleaned_Data!O2:O651) -> 45625433 | E5: =SUM(Cleaned_Data!Q2:Q651) -> 9426744.3 | G5: =IFERROR(C13/C12,0) -> 1.444375 | I5: =IFERROR(C12/C11,0) -> 0.66300608
A9: Month | B9: Net Sales | C9: Profit | E9: Category | F9: Net Sales | H9: Salesperson | I9: Net Sales | K9: Order Status | L9: Orders
A10: 46023 | B10: =SUMIFS(Cleaned_Data!$O:$O,Cleaned_Data!$B:$B,">="&A10,Cleaned_Data!$B:$B,"<"&EDATE(A10,1)) -> 4885314.4 | C10: =SUMIFS(Cleaned_Data!$Q:$Q,Cleaned_Data!$B:$B,">="&A10,Cleaned_Data!$B:$B,"<"&EDATE(A10,1)) -> 996608.71 | E10: Laptop | F10: =SUMIFS(Cleaned_Data!$O:$O,Cleaned_Data!$G:$G,E10) -> 29762238 | H10: Asha | I10: =SUMIFS(Cleaned_Data!$O:$O,Cleaned_Data!$C:$C,H10) -> 5668604.5 | K10: Delivered | L10: =COUNTIF(Cleaned_Data!$L:$L,K10) -> 330
A11: 46054 | B11: =SUMIFS(Cleaned_Data!$O:$O,Cleaned_Data!$B:$B,">="&A11,Cleaned_Data!$B:$B,"<"&EDATE(A11,1)) -> 5712651.9 | C11: =SUMIFS(Cleaned_Data!$Q:$Q,Cleaned_Data!$B:$B,">="&A11,Cleaned_Data!$B:$B,"<"&EDATE(A11,1)) -> 1212031.4 | E11: Monitor | F11: =SUMIFS(Cleaned_Data!$O:$O,Cleaned_Data!$G:$G,E11) -> 10991984 | H11: Ravi | I11: =SUMIFS(Cleaned_Data!$O:$O,Cleaned_Data!$C:$C,H11) -> 5315515.9 | K11: Pending | L11: =COUNTIF(Cleaned_Data!$L:$L,K11) -> 95
A12: 46082 | B12: =SUMIFS(Cleaned_Data!$O:$O,Cleaned_Data!$B:$B,">="&A12,Cleaned_Data!$B:$B,"<"&EDATE(A12,1)) -> 3723352.9 | C12: =SUMIFS(Cleaned_Data!$Q:$Q,Cleaned_Data!$B:$B,">="&A12,Cleaned_Data!$B:$B,"<"&EDATE(A12,1)) -> 803584.17 | E12: Keyboard | F12: =SUMIFS(Cleaned_Data!$O:$O,Cleaned_Data!$G:$G,E12) -> 1585946.6 | H12: Priya | I12: =SUMIFS(Cleaned_Data!$O:$O,Cleaned_Data!$C:$C,H12) -> 6463421.5 | K12: Cancelled | L12: =COUNTIF(Cleaned_Data!$L:$L,K12) -> 108
A13: 46113 | B13: =SUMIFS(Cleaned_Data!$O:$O,Cleaned_Data!$B:$B,">="&A13,Cleaned_Data!$B:$B,"<"&EDATE(A13,1)) -> 5144270.2 | C13: =SUMIFS(Cleaned_Data!$Q:$Q,Cleaned_Data!$B:$B,">="&A13,Cleaned_Data!$B:$B,"<"&EDATE(A13,1)) -> 1160676.9 | E13: Mouse | F13: =SUMIFS(Cleaned_Data!$O:$O,Cleaned_Data!$G:$G,E13) -> 1278533.1 | H13: Meghana | I13: =SUMIFS(Cleaned_Data!$O:$O,Cleaned_Data!$C:$C,H13) -> 6143733.8 | K13: Returned | L13: =COUNTIF(Cleaned_Data!$L:$L,K13) -> 117
A14: 46143 | B14: =SUMIFS(Cleaned_Data!$O:$O,Cleaned_Data!$B:$B,">="&A14,Cleaned_Data!$B:$B,"<"&EDATE(A14,1)) -> 5441464.7 | C14: =SUMIFS(Cleaned_Data!$Q:$Q,Cleaned_Data!$B:$B,">="&A14,Cleaned_Data!$B:$B,"<"&EDATE(A14,1)) -> 1078937.4 | E14: Headset | F14: =SUMIFS(Cleaned_Data!$O:$O,Cleaned_Data!$G:$G,E14) -> 2006730.8 | H14: Bhoomika | I14: =SUMIFS(Cleaned_Data!$O:$O,Cleaned_Data!$C:$C,H14) -> 4553023.4
A15: 46174 | B15: =SUMIFS(Cleaned_Data!$O:$O,Cleaned_Data!$B:$B,">="&A15,Cleaned_Data!$B:$B,"<"&EDATE(A15,1)) -> 5502775.5 | C15: =SUMIFS(Cleaned_Data!$Q:$Q,Cleaned_Data!$B:$B,">="&A15,Cleaned_Data!$B:$B,"<"&EDATE(A15,1)) -> 1079226.6 | H15: Arjun | I15: =SUMIFS(Cleaned_Data!$O:$O,Cleaned_Data!$C:$C,H15) -> 5969906.3
A16: 46204 | B16: =SUMIFS(Cleaned_Data!$O:$O,Cleaned_Data!$B:$B,">="&A16,Cleaned_Data!$B:$B,"<"&EDATE(A16,1)) -> 9441698.2 | C16: =SUMIFS(Cleaned_Data!$Q:$Q,Cleaned_Data!$B:$B,">="&A16,Cleaned_Data!$B:$B,"<"&EDATE(A16,1)) -> 1890210.6 | H16: Kiran | I16: =SUMIFS(Cleaned_Data!$O:$O,Cleaned_Data!$C:$C,H16) -> 5233823.5
A17: 46235 | B17: =SUMIFS(Cleaned_Data!$O:$O,Cleaned_Data!$B:$B,">="&A17,Cleaned_Data!$B:$B,"<"&EDATE(A17,1)) -> 4511273.6 | C17: =SUMIFS(Cleaned_Data!$Q:$Q,Cleaned_Data!$B:$B,">="&A17,Cleaned_Data!$B:$B,"<"&EDATE(A17,1)) -> 967086.96 | H17: Neha | I17: =SUMIFS(Cleaned_Data!$O:$O,Cleaned_Data!$C:$C,H17) -> 6277403.8
A18: 46266 | B18: =SUMIFS(Cleaned_Data!$O:$O,Cleaned_Data!$B:$B,">="&A18,Cleaned_Data!$B:$B,"<"&EDATE(A18,1)) -> 0 | C18: =SUMIFS(Cleaned_Data!$Q:$Q,Cleaned_Data!$B:$B,">="&A18,Cleaned_Data!$B:$B,"<"&EDATE(A18,1)) -> 0
A36: Salesperson Performance
A37: Salesperson | B37: Net Sales | C37: Profit | D37: Margin
A38: Asha | B38: =SUMIFS(Cleaned_Data!$O:$O,Cleaned_Data!$C:$C,A38) -> 5668604.5 | C38: =SUMIFS(Cleaned_Data!$Q:$Q,Cleaned_Data!$C:$C,A38) -> 1138324.8 | D38: =IFERROR(C38/B38,0) -> 0.20081218
A39: Ravi | B39: =SUMIFS(Cleaned_Data!$O:$O,Cleaned_Data!$C:$C,A39) -> 5315515.9 | C39: =SUMIFS(Cleaned_Data!$Q:$Q,Cleaned_Data!$C:$C,A39) -> 1145024 | D39: =IFERROR(C39/B39,0) -> 0.21541164
A40: Priya | B40: =SUMIFS(Cleaned_Data!$O:$O,Cleaned_Data!$C:$C,A40) -> 6463421.5 | C40: =SUMIFS(Cleaned_Data!$Q:$Q,Cleaned_Data!$C:$C,A40) -> 1399030.8 | D40: =IFERROR(C40/B40,0) -> 0.21645359
A41: Meghana | B41: =SUMIFS(Cleaned_Data!$O:$O,Cleaned_Data!$C:$C,A41) -> 6143733.8 | C41: =SUMIFS(Cleaned_Data!$Q:$Q,Cleaned_Data!$C:$C,A41) -> 1225488.1 | D41: =IFERROR(C41/B41,0) -> 0.1994696
A42: Bhoomika | B42: =SUMIFS(Cleaned_Data!$O:$O,Cleaned_Data!$C:$C,A42) -> 4553023.4 | C42: =SUMIFS(Cleaned_Data!$Q:$Q,Cleaned_Data!$C:$C,A42) -> 984316 | D42: =IFERROR(C42/B42,0) -> 0.21618953
A43: Arjun | B43: =SUMIFS(Cleaned_Data!$O:$O,Cleaned_Data!$C:$C,A43) -> 5969906.3 | C43: =SUMIFS(Cleaned_Data!$Q:$Q,Cleaned_Data!$C:$C,A43) -> 1258063.9 | D43: =IFERROR(C43/B43,0) -> 0.21073427
A44: Kiran | B44: =SUMIFS(Cleaned_Data!$O:$O,Cleaned_Data!$C:$C,A44) -> 5233823.5 | C44: =SUMIFS(Cleaned_Data!$Q:$Q,Cleaned_Data!$C:$C,A44) -> 1045224.5 | D44: =IFERROR(C44/B44,0) -> 0.19970572
A45: Neha | B45: =SUMIFS(Cleaned_Data!$O:$O,Cleaned_Data!$C:$C,A45) -> 6277403.8 | C45: =SUMIFS(Cleaned_Data!$Q:$Q,Cleaned_Data!$C:$C,A45) -> 1231272.3 | D45: =IFERROR(C45/B45,0) -> 0.19614355
